maicoin/__init__.py
maicoin/data/__init__.py
maicoin/data/action.py
maicoin/data/balance.py
maicoin/data/event.py
maicoin/data/order.py
maicoin/data/subscription.py
maicoin/data/ticker.py
maicoin/data/trade.py
maicoin/enums/__init__.py
maicoin/enums/action.py
maicoin/enums/channel.py
maicoin/enums/event.py
maicoin/enums/filter.py
maicoin/enums/order.py
maicoin/enums/side.py
maicoin/stream.py
maicoin/utils.py
maicoin-0.1.1.dist-info/LICENSE
maicoin-0.1.1.dist-info/METADATA
maicoin-0.1.1.dist-info/WHEEL
maicoin-0.1.1.dist-info/RECORD
