Metadata-Version: 2.1
Name: maicoin
Version: 0.1.1
Summary: 
Author: narumi
Author-email: toucans-cutouts0f@icloud.com
Requires-Python: >=3.9,<4.0
Classifier: Programming Language :: Python :: 3
Classifier: Programming Language :: Python :: 3.9
Classifier: Programming Language :: Python :: 3.10
Classifier: Programming Language :: Python :: 3.11
Requires-Dist: loguru (>=0.6.0,<0.7.0)
Requires-Dist: python-dotenv (>=1.0.0,<2.0.0)
Requires-Dist: websockets (>=10.2,<11.0)
